signal_processing_utilities/__init__.py
signal_processing_utilities/process_signal.py
signal_processing_utilities-0.1.23.dist-info/LICENSE
signal_processing_utilities-0.1.23.dist-info/METADATA
signal_processing_utilities-0.1.23.dist-info/WHEEL
signal_processing_utilities-0.1.23.dist-info/top_level.txt
signal_processing_utilities-0.1.23.dist-info/RECORD
