Metadata-Version: 2.1
Name: signal_processing_utilities
Version: 0.1.23
Summary: Tools that process neural signal.
Author: Evan Woods
Maintainer: Evan Woods
License: MIT License
Project-URL: Homepage, https://github.com/efwoods/signal_processing_utilities
Project-URL: Issues, https://github.com/efwoods/signal_processing_utilities/issues
Requires-Python: >=3.10
License-File: LICENSE
Requires-Dist: numpy >=1.0
Requires-Dist: scipy
